CHANGES.txt
README.txt
setup.cfg
setup.py
src/erp5/__init__.py
src/erp5.recipe.apache.egg-info/PKG-INFO
src/erp5.recipe.apache.egg-info/SOURCES.txt
src/erp5.recipe.apache.egg-info/dependency_links.txt
src/erp5.recipe.apache.egg-info/entry_points.txt
src/erp5.recipe.apache.egg-info/namespace_packages.txt
src/erp5.recipe.apache.egg-info/requires.txt
src/erp5.recipe.apache.egg-info/top_level.txt
src/erp5/recipe/__init__.py
src/erp5/recipe/apache/__init__.py
src/erp5/recipe/apache/templates/openssl.cnf.in
src/erp5/recipe/apache/templates/zope.conf.in
src/erp5/recipe/apache/templates/zope.conf.path.in