Metadata-Version: 1.0
Name: erp5.recipe.apache
Version: 1.0.dev-r41446
Summary: zc.buildout recipe to create apache instances which serversZope content
Home-page: https://svn.erp5.org/repos/public/erp5/trunk/utils/erp5.recipe.apache/
Author: Łukasz Nowak
Author-email: luke@nexedi.com
License: ZPL 2.1
Keywords: apache server buildout
Platform: UNKNOWN
Classifier: License :: OSI Approved :: Zope Public License
Classifier: Framework :: Buildout
